{"_type":"export","__export_format":4,"__export_date":"2021-05-17T01:45:08.751Z","__export_source":"insomnia.desktop.app:v2021.2.2","resources":[{"_id":"req_7023ee7676f94a3f8ef1f764623126c6","parentId":"fld_f77e593807db4af2bf8da539a03c40ac","modified":1621211308889,"created":1621025984723,"url":"{{host}}/graphql","name":"login","description":"","method":"POST","body":{"mimeType":"application/graphql","text":"{\"query\":\"mutation ($credentials: LoginInput!) {\\n  login(credentials: $credentials) {\\n    userId\\n    authorization\\n    profile {\\n       _id\\n      firstName\\n      lastName\\n      role\\n      username\\n      createdAt\\n      updatedAt\\n    }\\n  }\\n}\\n\",\"variables\":{\"credentials\":{\"username\":\"mbenslimen1\",\"password\":\"Mohamed1234\"}}}"},"parameters":[],"headers":[{"name":"Content-Type","value":"application/json","id":"pair_6bfc8f3646914249b4390fde958d5e9a"}],"authentication":{},"metaSortKey":-1621025984723,"isPrivate":false,"settingStoreCookies":true,"settingSendCookies":true,"settingDisableRenderRequestBody":false,"settingEncodeUrl":true,"settingRebuildPath":true,"settingFollowRedirects":"global","_type":"request"},{"_id":"fld_f77e593807db4af2bf8da539a03c40ac","parentId":"wrk_ed57f2ed3fee427d8cb2997bfaf863dc","modified":1621025972937,"created":1621025972937,"name":"Auth","description":"","environment":{},"environmentPropertyOrder":null,"metaSortKey":-1621025972937,"_type":"request_group"},{"_id":"wrk_ed57f2ed3fee427d8cb2997bfaf863dc","parentId":null,"modified":1621113903445,"created":1619358537521,"name":"AOS","description":"","scope":"collection","_type":"workspace"},{"_id":"req_2e6dfa72adbd409fbeda80023faa620a","parentId":"fld_f77e593807db4af2bf8da539a03c40ac","modified":1621209799171,"created":1621067543048,"url":"{{host}}/graphql","name":"logout","description":"","method":"POST","body":{"mimeType":"application/graphql","text":"{\"query\":\"mutation{logout}\"}"},"parameters":[],"headers":[{"name":"Content-Type","value":"application/json","id":"pair_9792a2cea189490686f7cca5c75043d3"}],"authentication":{},"metaSortKey":-1621025984673,"isPrivate":false,"settingStoreCookies":true,"settingSendCookies":true,"settingDisableRenderRequestBody":false,"settingEncodeUrl":true,"settingRebuildPath":true,"settingFollowRedirects":"global","_type":"request"},{"_id":"req_96e9df6e389e4a24a5a404fbae2362c1","parentId":"fld_f41ae6e5d72e4485b0896cc409fa7462","modified":1621215866767,"created":1621023512565,"url":"{{host}}/graphql","name":"create","description":"","method":"POST","body":{"mimeType":"application/graphql","text":"{\"query\":\"mutation ($user: CreateUserInput!) {\\n  user_create(\\n    user: $user\\n  ) {\\n    _id\\n    firstName\\n    lastName\\n    username\\n    role\\n    createdAt\\n    updatedAt\\n  }\\n}\\n\",\"variables\":{\"user\":{\"firstName\":\"Mohamed Ali\",\"lastName\":\"Ben Slimen\",\"password\":\"Mohamed1234\",\"role\":\"user\"}}}"},"parameters":[],"headers":[{"name":"Content-Type","value":"application/json","id":"pair_d4adb61efd404f109bc2e04b6bb0f40f"}],"authentication":{},"metaSortKey":-1621077345270,"isPrivate":false,"settingStoreCookies":true,"settingSendCookies":true,"settingDisableRenderRequestBody":false,"settingEncodeUrl":true,"settingRebuildPath":true,"settingFollowRedirects":"global","_type":"request"},{"_id":"fld_f41ae6e5d72e4485b0896cc409fa7462","parentId":"wrk_ed57f2ed3fee427d8cb2997bfaf863dc","modified":1621023444973,"created":1621023444974,"name":"User","description":"","environment":{},"environmentPropertyOrder":null,"metaSortKey":-1621023444974,"_type":"request_group"},{"_id":"req_fd47fac0f9924372a6b889d2802b4730","parentId":"fld_f41ae6e5d72e4485b0896cc409fa7462","modified":1621210522119,"created":1621077345220,"url":"{{host}}/graphql","name":"one","description":"","method":"POST","body":{"mimeType":"application/graphql","text":"{\"query\":\"query($_id: String!) {\\n  user(_id: $_id) {\\n    _id\\n    firstName\\n    lastName\\n    username\\n    role\\n    createdAt\\n    updatedAt\\n  }\\n}\\n\",\"variables\":{\"_id\":\"60a1b2f62f0f52429837410e\"}}"},"parameters":[],"headers":[{"name":"Content-Type","value":"application/json","id":"pair_f01541d1cfb14b51a22dd4bd185537e2"}],"authentication":{},"metaSortKey":-1621077345220,"isPrivate":false,"settingStoreCookies":true,"settingSendCookies":true,"settingDisableRenderRequestBody":false,"settingEncodeUrl":true,"settingRebuildPath":true,"settingFollowRedirects":"global","_type":"request"},{"_id":"req_9d92736c7d9a43da9d151edb724c1f09","parentId":"fld_f41ae6e5d72e4485b0896cc409fa7462","modified":1621185268305,"created":1621024390586,"url":"{{host}}/graphql","name":"list","description":"","method":"POST","body":{"mimeType":"application/graphql","text":"{\"query\":\"query($filters: UserFilters!, $pagination: paginationInput!) {\\n  user_list(filters: $filters, pagination: $pagination) {\\n    list {\\n      _id\\n      firstName\\n      lastName\\n      role\\n      username\\n      createdAt\\n      updatedAt\\n    }\\n    pagination {\\n      page\\n      total\\n      totalPages\\n    }\\n  }\\n}\\n\",\"variables\":{\"filters\":{},\"pagination\":{\"page\":1,\"size\":10}}}"},"parameters":[],"headers":[{"name":"Content-Type","value":"application/json","id":"pair_5b14573065f644f6a29b3d320a16289e"}],"authentication":{},"metaSortKey":-1621039098672.5,"isPrivate":false,"settingStoreCookies":true,"settingSendCookies":true,"settingDisableRenderRequestBody":false,"settingEncodeUrl":true,"settingRebuildPath":true,"settingFollowRedirects":"global","_type":"request"},{"_id":"req_43397ed6052d4d209cf98c1b01d78663","parentId":"fld_f41ae6e5d72e4485b0896cc409fa7462","modified":1621215835775,"created":1621190310673,"url":"{{host}}/graphql","name":"update password","description":"","method":"POST","body":{"mimeType":"application/graphql","text":"{\"query\":\"mutation($passwords: UpdatePasswordInput!) {user_password_update(passwords: $passwords)}\\n\",\"variables\":{\"passwords\":{\"oldPassword\":\"Admin123\",\"newPassword\":\"Dali1234\"}}}"},"parameters":[],"headers":[{"name":"Content-Type","value":"application/json","id":"pair_6b292e8365a74ac9964fedb7fd8039da"}],"authentication":{},"metaSortKey":-1621039098663.125,"isPrivate":false,"settingStoreCookies":true,"settingSendCookies":true,"settingDisableRenderRequestBody":false,"settingEncodeUrl":true,"settingRebuildPath":true,"settingFollowRedirects":"global","_type":"request"},{"_id":"req_d1ad7a4579dc42b6af086238798974cc","parentId":"fld_f41ae6e5d72e4485b0896cc409fa7462","modified":1621187809790,"created":1621078192371,"url":"{{host}}/graphql","name":"update","description":"","method":"POST","body":{"mimeType":"application/graphql","text":"{\"query\":\"mutation ($user: UpdateUserInput!) {\\n  user_update(user: $user)\\n}\\n\",\"variables\":{\"user\":{\"_id\":\"609fa68b94cf7f2b3cbdeeb1\",\"firstName\":\"new firstname\",\"lastName\":\"new lastname\"}}}"},"parameters":[],"headers":[{"name":"Content-Type","value":"application/json","id":"pair_0d5c0ef66ab9445fb5073d43480e8b0d"}],"authentication":{},"metaSortKey":-1621039098653.75,"isPrivate":false,"settingStoreCookies":true,"settingSendCookies":true,"settingDisableRenderRequestBody":false,"settingEncodeUrl":true,"settingRebuildPath":true,"settingFollowRedirects":"global","_type":"request"},{"_id":"req_27e6a69e671645088992c250fe0163d7","parentId":"fld_f41ae6e5d72e4485b0896cc409fa7462","modified":1621190296108,"created":1621039098635,"url":"{{host}}/graphql","name":"delete","description":"","method":"POST","body":{"mimeType":"application/graphql","text":"{\"query\":\"mutation($_id: String!){user_delete(_id: $_id)}\",\"variables\":{\"_id\":\"609f18ee9fe7754bf0fbbce2\"}}"},"parameters":[],"headers":[{"name":"Content-Type","value":"application/json","id":"pair_63be706090b7469f92ef487ee494310e"}],"authentication":{},"metaSortKey":-1621039098635,"isPrivate":false,"settingStoreCookies":true,"settingSendCookies":true,"settingDisableRenderRequestBody":false,"settingEncodeUrl":true,"settingRebuildPath":true,"settingFollowRedirects":"global","_type":"request"},{"_id":"req_09acdc0fa5904b0ab1147ede72ee3e67","parentId":"fld_43b5b27ebf7849cb83101ac2443cc2c4","modified":1621214092310,"created":1621022128753,"url":"{{host}}/graphql","name":"create","description":"","method":"POST","body":{"mimeType":"application/graphql","text":"{\"query\":\"mutation($task: CreateTaskInput!) {\\n  task_create(task: $task) {\\n    _id\\n    title\\n    description\\n    owner(populate: true) {\\n      _id\\n    }\\n  }\\n}\\n\",\"variables\":{\"task\":{\"title\":\"task title\",\"description\":\"task description\"}}}"},"parameters":[],"headers":[{"name":"Content-Type","value":"application/json","id":"pair_769c3d3cd53b4f11b7a2d7e77fa12815"}],"authentication":{},"metaSortKey":-1621022522203,"isPrivate":false,"settingStoreCookies":true,"settingSendCookies":true,"settingDisableRenderRequestBody":false,"settingEncodeUrl":true,"settingRebuildPath":true,"settingFollowRedirects":"global","_type":"request"},{"_id":"fld_43b5b27ebf7849cb83101ac2443cc2c4","parentId":"wrk_ed57f2ed3fee427d8cb2997bfaf863dc","modified":1621022090017,"created":1621022090017,"name":"Task","description":"","environment":{},"environmentPropertyOrder":null,"metaSortKey":-1621022090017,"_type":"request_group"},{"_id":"req_5f06372c79064cc3a57dcc2e049a61c4","parentId":"fld_43b5b27ebf7849cb83101ac2443cc2c4","modified":1621211313348,"created":1621079528350,"url":"{{host}}/graphql","name":"one","description":"","method":"POST","body":{"mimeType":"application/graphql","text":"{\"query\":\"query ($_id: String!){\\n  task(_id: $_id) {\\n    _id\\n    title\\n    description\\n    owner(populate: true) {\\n      _id\\n      firstName\\n      lastName\\n      role\\n      username\\n      createdAt\\n      updatedAt\\n    }\\n    sharedWith(populate: true) {\\n      _id\\n      firstName\\n      lastName\\n      role\\n      username\\n      createdAt\\n      updatedAt\\n    }\\n    completed\\n    createdAt\\n    updatedAt\\n  }\\n}\\n\",\"variables\":{\"_id\":\"60a1b2f62f0f52429837410e\"}}"},"parameters":[],"headers":[{"name":"Content-Type","value":"application/json","id":"pair_e18415251136470a80a85fa418080060"}],"authentication":{},"metaSortKey":-1621022423815.5,"isPrivate":false,"settingStoreCookies":true,"settingSendCookies":true,"settingDisableRenderRequestBody":false,"settingEncodeUrl":true,"settingRebuildPath":true,"settingFollowRedirects":"global","_type":"request"},{"_id":"req_ad7cf95fbd19479e9f936222d114a3b3","parentId":"fld_43b5b27ebf7849cb83101ac2443cc2c4","modified":1621205538993,"created":1621081126651,"url":"{{host}}/graphql","name":"list","description":"","method":"POST","body":{"mimeType":"application/graphql","text":"{\"query\":\"query($filters: TaskFilters!, $pagination: paginationInput!) {\\n  task_list(filters: $filters, pagination: $pagination) {\\n    list {\\n      _id\\n      title\\n      description\\n      owner(populate: true) {\\n        _id\\n        firstName\\n        lastName\\n        role\\n        username\\n        createdAt\\n        updatedAt\\n      }\\n      sharedWith(populate: true) {\\n        _id\\n        firstName\\n        lastName\\n        role\\n        username\\n        createdAt\\n        updatedAt\\n      }\\n      completed\\n      createdAt\\n      updatedAt\\n    }\\n    pagination {\\n      page\\n      size\\n      total\\n      totalPages\\n    }\\n  }\\n}\\n\",\"variables\":{\"filters\":{},\"pagination\":{\"page\":1,\"size\":10}}}"},"parameters":[],"headers":[{"name":"Content-Type","value":"application/json","id":"pair_b660004e0f29491e852ddfab2cc2d806"}],"authentication":{},"metaSortKey":-1621022374621.75,"isPrivate":false,"settingStoreCookies":true,"settingSendCookies":true,"settingDisableRenderRequestBody":false,"settingEncodeUrl":true,"settingRebuildPath":true,"settingFollowRedirects":"global","_type":"request"},{"_id":"req_2c1b6495e0bd4139b986d99466438ed8","parentId":"fld_43b5b27ebf7849cb83101ac2443cc2c4","modified":1621214690806,"created":1621077014428,"url":"{{host}}/graphql","name":"update","description":"","method":"POST","body":{"mimeType":"application/graphql","text":"{\"query\":\"mutation ($task: UpdateTaskInput!) {\\n  task_update(task: $task)\\n}\\n\",\"variables\":{\"task\":{\"_id\":\"609f99ee16841532c4333d95\",\"title\":\"new title\",\"description\":\"new description\"}}}"},"parameters":[],"headers":[{"name":"Content-Type","value":"application/json","id":"pair_1fb028d48662470eb737c19428d1e287"}],"authentication":{},"metaSortKey":-1621022325428,"isPrivate":false,"settingStoreCookies":true,"settingSendCookies":true,"settingDisableRenderRequestBody":false,"settingEncodeUrl":true,"settingRebuildPath":true,"settingFollowRedirects":"global","_type":"request"},{"_id":"req_bfa23db272bc4717b8d82ba86afb7010","parentId":"fld_43b5b27ebf7849cb83101ac2443cc2c4","modified":1621214734706,"created":1621081474795,"url":"{{host}}/graphql","name":"update ( mark as completed )","description":"","method":"POST","body":{"mimeType":"application/graphql","text":"{\"query\":\"mutation($task: UpdateTaskInput!) {\\n  task_update(task: $task)\\n}\\n\",\"variables\":{\"task\":{\"_id\":\"609f99ee16841532c4333d95\",\"completed\":true}}}"},"parameters":[],"headers":[{"name":"Content-Type","value":"application/json","id":"pair_69e526edd76249598293db99a8b6e2d5"}],"authentication":{},"metaSortKey":-1621022227015.5,"isPrivate":false,"settingStoreCookies":true,"settingSendCookies":true,"settingDisableRenderRequestBody":false,"settingEncodeUrl":true,"settingRebuildPath":true,"settingFollowRedirects":"global","_type":"request"},{"_id":"req_f51f154dbb7146119e7147ee2946e61d","parentId":"fld_43b5b27ebf7849cb83101ac2443cc2c4","modified":1621214406884,"created":1621022522153,"url":"{{host}}/graphql","name":"delete","description":"","method":"POST","body":{"mimeType":"application/graphql","text":"{\"query\":\"mutation($_id: String!){task_delete(_id: $_id)}\",\"variables\":{\"_id\":\"60a19661c96d6010d03bf36d\"}}"},"parameters":[],"headers":[{"name":"Content-Type","value":"application/json","id":"pair_a10737c5c2094e57838814c14502c9e4"}],"authentication":{},"metaSortKey":-1621022128603,"isPrivate":false,"settingStoreCookies":true,"settingSendCookies":true,"settingDisableRenderRequestBody":false,"settingEncodeUrl":true,"settingRebuildPath":true,"settingFollowRedirects":"global","_type":"request"},{"_id":"req_ac02586259a04637b228fe25db94e7da","parentId":"fld_43b5b27ebf7849cb83101ac2443cc2c4","modified":1621214135792,"created":1621076485290,"url":"{{host}}/graphql","name":"share","description":"","method":"POST","body":{"mimeType":"application/graphql","text":"{\"query\":\"mutation ($taskId: String!, $userId: String!) {\\n  task_share(taskId: $taskId, userId: $userId)\\n}\",\"variables\":{\"taskId\":\"60a1c1bf3ffd082038c58a11\",\"userId\":\"60a1b2b02f0f52429837410d\"}}"},"parameters":[],"headers":[{"name":"Content-Type","value":"application/json","id":"pair_e807962918a74e5ca39411f7b7905550"}],"authentication":{},"metaSortKey":-1621022128553,"isPrivate":false,"settingStoreCookies":true,"settingSendCookies":true,"settingDisableRenderRequestBody":false,"settingEncodeUrl":true,"settingRebuildPath":true,"settingFollowRedirects":"global","_type":"request"},{"_id":"req_309194d6efc54784942f7efa8d00a6b2","parentId":"fld_43b5b27ebf7849cb83101ac2443cc2c4","modified":1621211288366,"created":1621076514885,"url":"{{host}}/graphql","name":"unlink","description":"","method":"POST","body":{"mimeType":"application/graphql","text":"{\"query\":\"mutation ($taskId: String!, $userId: String!) {\\n  task_unlink(taskId: $taskId, userId: $userId)\\n}\\n\",\"variables\":{\"taskId\":\"60a1b2f62f0f52429837410e\",\"userId\":\"60a1b2b02f0f52429837410d\"}}"},"parameters":[],"headers":[{"name":"Content-Type","value":"application/json","id":"pair_c72cf7f3f80245089276b0cfb22d2240"}],"authentication":{},"metaSortKey":-1621022128503,"isPrivate":false,"settingStoreCookies":true,"settingSendCookies":true,"settingDisableRenderRequestBody":false,"settingEncodeUrl":true,"settingRebuildPath":true,"settingFollowRedirects":"global","_type":"request"},{"_id":"req_42fe7447d423430db537915805694a32","parentId":"fld_2b88ef96fe634f47b70c83a7a318e1db","modified":1621205876269,"created":1621082154009,"url":"{{host}}/graphql","name":"create","description":"","method":"POST","body":{"mimeType":"application/graphql","text":"{\"query\":\"mutation ($comment: CreateCommentInput!) {\\n  comment_create(\\n    comment: $comment\\n  ) {\\n    _id\\n    user(populate: true) {_id, firstName}\\n    task(populate: true) {\\n      _id\\n      title\\n      description\\n      owner(populate:true) {_id, firstName}\\n      sharedWith(populate:true) {_id, firstName}\\n      completed\\n      createdAt\\n      updatedAt\\n    }\\n    content\\n    createdAt\\n    updatedAt\\n  }\\n}\\n\",\"variables\":{\"comment\":{\"task\":\"609fd4f8724a284858e5da47\",\"content\":\"this is comment content\"}}}"},"parameters":[],"headers":[{"name":"Content-Type","value":"application/json","id":"pair_7924ca1028624b8086ab97d2d7a83cb1"}],"authentication":{},"metaSortKey":-1621082154009,"isPrivate":false,"settingStoreCookies":true,"settingSendCookies":true,"settingDisableRenderRequestBody":false,"settingEncodeUrl":true,"settingRebuildPath":true,"settingFollowRedirects":"global","_type":"request"},{"_id":"fld_2b88ef96fe634f47b70c83a7a318e1db","parentId":"wrk_ed57f2ed3fee427d8cb2997bfaf863dc","modified":1621077240691,"created":1621077238570,"name":"Comment","description":"","environment":{},"environmentPropertyOrder":null,"metaSortKey":-1621022089967,"_type":"request_group"},{"_id":"req_99c0d6092cb24ccfa67a47446fcb7563","parentId":"fld_2b88ef96fe634f47b70c83a7a318e1db","modified":1621206149609,"created":1621100427188,"url":"{{host}}/graphql","name":"one","description":"","method":"POST","body":{"mimeType":"application/graphql","text":"{\"query\":\"query ($_id: String!) {\\n  comment(_id: $_id) {\\n    _id\\n    content\\n    createdAt\\n    updatedAt\\n    user(populate: true) {\\n      _id\\n      firstName\\n      lastName\\n      username\\n      createdAt\\n      updatedAt\\n    }\\n  }\\n}\\n\",\"variables\":{\"_id\":\"609fd506724a284858e5da48\"}}"},"parameters":[],"headers":[{"name":"Content-Type","value":"application/json","id":"pair_d32ab471fdc64bc8acf4c280669c9c5b"}],"authentication":{},"metaSortKey":-1621082154002.75,"isPrivate":false,"settingStoreCookies":true,"settingSendCookies":true,"settingDisableRenderRequestBody":false,"settingEncodeUrl":true,"settingRebuildPath":true,"settingFollowRedirects":"global","_type":"request"},{"_id":"req_6dc1324c94134167ab554f6a0bead70b","parentId":"fld_2b88ef96fe634f47b70c83a7a318e1db","modified":1621215832333,"created":1621100744942,"url":"{{host}}/graphql","name":"list ( by task )","description":"","method":"POST","body":{"mimeType":"application/graphql","text":"{\"query\":\"query($taskId: String!) {\\n  comment_list(taskId: $taskId) {\\n    _id\\n    content\\n    createdAt\\n    updatedAt\\n    user(populate: true) {\\n      _id\\n      firstName\\n      lastName\\n      username\\n      createdAt\\n      updatedAt\\n    }\\n  }\\n}\\n\",\"variables\":{\"taskId\":\"609fd4f8724a284858e5da47\"}}"},"parameters":[],"headers":[{"name":"Content-Type","value":"application/json","id":"pair_de58f4ae535645f8af028b5237f8c8ab"}],"authentication":{},"metaSortKey":-1621082153996.5,"isPrivate":false,"settingStoreCookies":true,"settingSendCookies":true,"settingDisableRenderRequestBody":false,"settingEncodeUrl":true,"settingRebuildPath":true,"settingFollowRedirects":"global","_type":"request"},{"_id":"req_4ac68e7a439d4eeaab2b4ec527716d14","parentId":"fld_2b88ef96fe634f47b70c83a7a318e1db","modified":1621206026720,"created":1621101393052,"url":"{{host}}/graphql","name":"update","description":"","method":"POST","body":{"mimeType":"application/graphql","text":"{\"query\":\"mutation ($comment: UpdateCommentInput!) {\\n  comment_update(comment: $comment)\\n}\\n\",\"variables\":{\"comment\":{\"_id\":\"609fd506724a284858e5da48\",\"content\":\"new comment content\"}}}"},"parameters":[],"headers":[{"name":"Content-Type","value":"application/json","id":"pair_2727cd4929694ecaa69c03302bb1f0d0"}],"authentication":{},"metaSortKey":-1621082153977.75,"isPrivate":false,"settingStoreCookies":true,"settingSendCookies":true,"settingDisableRenderRequestBody":false,"settingEncodeUrl":true,"settingRebuildPath":true,"settingFollowRedirects":"global","_type":"request"},{"_id":"req_ae2edc118dbf4ad0b4ee0350a6830b2b","parentId":"fld_2b88ef96fe634f47b70c83a7a318e1db","modified":1621206104120,"created":1621085501468,"url":"{{host}}/graphql","name":"delete","description":"","method":"POST","body":{"mimeType":"application/graphql","text":"{\"query\":\"mutation($_id: String!){comment_delete(_id: $_id )}\",\"variables\":{\"_id\":\"609fcbbe49f6d04b2883dcc0\"}}"},"parameters":[],"headers":[{"name":"Content-Type","value":"application/json","id":"pair_8189cbb526e64479a5bff098a7ea0f56"}],"authentication":{},"metaSortKey":-1621082153959,"isPrivate":false,"settingStoreCookies":true,"settingSendCookies":true,"settingDisableRenderRequestBody":false,"settingEncodeUrl":true,"settingRebuildPath":true,"settingFollowRedirects":"global","_type":"request"},{"_id":"env_169380dbb0db8983480c7c720c844136acea75b1","parentId":"wrk_ed57f2ed3fee427d8cb2997bfaf863dc","modified":1621024544599,"created":1619358537566,"name":"Base Environment","data":{},"dataPropertyOrder":{},"color":null,"isPrivate":false,"metaSortKey":1619358537566,"_type":"environment"},{"_id":"jar_169380dbb0db8983480c7c720c844136acea75b1","parentId":"wrk_ed57f2ed3fee427d8cb2997bfaf863dc","modified":1621211311031,"created":1619358537569,"name":"Default Jar","cookies":[{"key":"authorization","value":"eyJhbGciOiJIUzI1NiIsInR5cCI6IkpXVCJ9.eyJfaWQiOiI2MGExYjJiMDJmMGY1MjQyOTgzNzQxMGQiLCJyb2xlIjoidXNlciIsImlhdCI6MTYyMTIxMTMxMSwiZXhwIjoxNjIxMjk3NzExfQ.ErlaC5cA_dk_49HH6flJ02_YEqdAITBS1dMD0j-Zd2U","domain":"localhost","path":"/","httpOnly":true,"extensions":["SameSite=Strict"],"hostOnly":true,"creation":"2021-05-14T22:26:20.987Z","lastAccessed":"2021-05-17T00:28:31.031Z","id":"7735311609732858"},{"key":"userId","value":"j%3A%2260a1b2b02f0f52429837410d%22","domain":"localhost","path":"/","httpOnly":true,"extensions":["SameSite=Strict"],"hostOnly":true,"creation":"2021-05-14T22:26:20.987Z","lastAccessed":"2021-05-17T00:28:31.031Z","id":"8830069839546162"}],"_type":"cookie_jar"},{"_id":"spc_d08b4c6977a04ab0a55c080007089e02","parentId":"wrk_ed57f2ed3fee427d8cb2997bfaf863dc","modified":1619358537521,"created":1619358537521,"fileName":"Insomnia","contents":"","contentType":"yaml","_type":"api_spec"},{"_id":"env_45c6761c62774aafbb39db900ee29ac8","parentId":"env_169380dbb0db8983480c7c720c844136acea75b1","modified":1621024576873,"created":1621024531026,"name":"production","data":{"host":"http://localhost:3000"},"dataPropertyOrder":{"&":["host"]},"color":null,"isPrivate":false,"metaSortKey":1621024531026,"_type":"environment"},{"_id":"env_74bfa0d0c3404602a3a11ee8bb742065","parentId":"env_169380dbb0db8983480c7c720c844136acea75b1","modified":1621024564417,"created":1621024548337,"name":"dev","data":{"host":"http://localhost:3001"},"dataPropertyOrder":{"&":["host"]},"color":null,"isPrivate":false,"metaSortKey":1621024548337,"_type":"environment"}]}